xxkcd/__init__.py
xxkcd/_cache.py
xxkcd/_html_parsing.py
xxkcd/_util.py
xxkcd/constants.py
xxkcd/metadata.py
xxkcd/what_if.py
xxkcd/xkcd.py
xxkcd-1.4.0.dist-info/DESCRIPTION.rst
xxkcd-1.4.0.dist-info/METADATA
xxkcd-1.4.0.dist-info/RECORD
xxkcd-1.4.0.dist-info/WHEEL
xxkcd-1.4.0.dist-info/metadata.json
xxkcd-1.4.0.dist-info/top_level.txt
