Metadata-Version: 2.0
Name: xxkcd
Version: 1.4.0
Summary: An (unofficial) Python wrapper around xkcd APIs
Home-page: https://github.com/MitalAshok/xxkcd
Author: Mital Ashok
Author-email: mital.vaja@googlemail.com
License: MIT
Keywords: xkcd,api,wrapper,what-if
Platform: any
Classifier: Development Status :: 3 - Alpha
Classifier: Intended Audience :: Developers
Classifier: License :: OSI Approved :: MIT License
Classifier: Operating System :: OS Independent
Classifier: Programming Language :: Python :: 2
Classifier: Programming Language :: Python :: 2.7
Classifier: Programming Language :: Python :: 3
Classifier: Programming Language :: Python :: 3.4
Classifier: Programming Language :: Python :: 3.5
Classifier: Programming Language :: Python :: 3.6
Classifier: Topic :: Internet :: WWW/HTTP :: Indexing/Search
Requires-Dist: objecttools (>=1.0.1)
